impressify/impressify.py
impressify-1.3.1.dist-info/METADATA
impressify-1.3.1.dist-info/WHEEL
impressify-1.3.1.dist-info/entry_points.txt
impressify-1.3.1.dist-info/RECORD
